{"data_mtime": 1682607295, "dep_lines": [12, 3, 4, 5, 6, 7, 9, 1, 1, 1, 1, 1, 1, 1, 1, 1, 1, 11], "dep_prios": [5, 10, 10, 10, 5, 5, 5, 5, 20, 20, 30, 30, 30, 30, 30, 30, 30, 5], "dependencies": ["black.mode", "os", "pickle", "tempfile", "pathlib", "typing", "platformdirs", "builtins", "pyexpat.errors", "pyexpat.model", "_typeshed", "abc", "array", "ctypes", "io", "mmap", "typing_extensions"], "hash": "c82f1a0a2386a4dab692ab2bb525028e31fa3664d732450a83d80ef70e295048", "id": "black.cache", "ignore_all": true, "interface_hash": "20ee330b7f3c1b5e3b23cfdafd30461fd11516a6e1ec546defb9ebc54e127b96", "mtime": 1676471288, "options": {"allow_redefinition": false, "allow_untyped_globals": false, "always_false": [], "always_true": [], "bazel": false, "check_untyped_defs": false, "disable_bytearray_promotion": false, "disable_error_code": [], "disable_memoryview_promotion": false, "disabled_error_codes": [], "disallow_any_decorated": false, "disallow_any_explicit": false, "disallow_any_expr": false, "disallow_any_generics": false, "disallow_any_unimported": false, "disallow_incomplete_defs": false, "disallow_subclassing_any": false, "disallow_untyped_calls": false, "disallow_untyped_decorators": false, "disallow_untyped_defs": false, "enable_error_code": [], "enabled_error_codes": [], "follow_imports": "silent", "follow_imports_for_stubs": false, "ignore_errors": false, "ignore_missing_imports": true, "implicit_optional": false, "implicit_reexport": true, "local_partial_types": false, "mypyc": false, "platform": "darwin", "plugins": [], "strict_concatenate": false, "strict_equality": false, "strict_optional": true, "warn_no_return": true, "warn_return_any": false, "warn_unreachable": true, "warn_unused_ignores": false}, "path": "/Users/willmcgugan/.pyenv/versions/3.11.1/envs/textual/lib/python3.11/site-packages/black/cache.py", "plugin_data": null, "size": 2946, "suppressed": ["_black_version"], "version_id": "1.1.1"}