{".class":"MypyFile","_fullname":"tree_sitter_xml","future_import_flags":[],"is_partial_stub_package":false,"is_stub":true,"names":{".class":"SymbolTable","__annotations__":{".class":"SymbolTableNode","kind":"Gdef","node":{".class":"Var","flags":["is_ready"],"fullname":"tree_sitter_xml.__annotations__","name":"__annotations__","type":{".class":"Instance","args":["builtins.str",{".class":"AnyType","missing_import_name":null,"source_any":null,"type_of_any":6}],"extra_attrs":null,"type_ref":"builtins.dict"}}},"__doc__":{".class":"SymbolTableNode","kind":"Gdef","node":{".class":"Var","flags":["is_ready"],"fullname":"tree_sitter_xml.__doc__","name":"__doc__","type":"builtins.str"}},"__file__":{".class":"SymbolTableNode","kind":"Gdef","node":{".class":"Var","flags":["is_ready"],"fullname":"tree_sitter_xml.__file__","name":"__file__","type":"builtins.str"}},"__name__":{".class":"SymbolTableNode","kind":"Gdef","node":{".class":"Var","flags":["is_ready"],"fullname":"tree_sitter_xml.__name__","name":"__name__","type":"builtins.str"}},"__package__":{".class":"SymbolTableNode","kind":"Gdef","node":{".class":"Var","flags":["is_ready"],"fullname":"tree_sitter_xml.__package__","name":"__package__","type":"builtins.str"}},"__path__":{".class":"SymbolTableNode","kind":"Gdef","node":{".class":"Var","flags":["is_ready"],"fullname":"tree_sitter_xml.__path__","name":"__path__","type":{".class":"Instance","args":["builtins.str"],"extra_attrs":null,"type_ref":"builtins.list"}}},"__spec__":{".class":"SymbolTableNode","kind":"Gdef","node":{".class":"Var","flags":["is_ready"],"fullname":"tree_sitter_xml.__spec__","name":"__spec__","type":"importlib.machinery.ModuleSpec"}},"language_dtd":{".class":"SymbolTableNode","kind":"Gdef","node":{".class":"FuncDef","abstract_status":0,"arg_kinds":[],"arg_names":[],"dataclass_transform_spec":null,"flags":[],"fullname":"tree_sitter_xml.language_dtd","name":"language_dtd","type":{".class":"CallableType","arg_kinds":[],"arg_names":[],"arg_types":[],"bound_args":[],"def_extras":{"first_arg":null},"fallback":"builtins.function","from_concatenate":false,"implicit":false,"imprecise_arg_kinds":false,"is_ellipsis_args":false,"name":"language_dtd","ret_type":"builtins.object","type_guard":null,"type_is":null,"unpack_kwargs":false,"variables":[]}}},"language_xml":{".class":"SymbolTableNode","kind":"Gdef","node":{".class":"FuncDef","abstract_status":0,"arg_kinds":[],"arg_names":[],"dataclass_transform_spec":null,"flags":[],"fullname":"tree_sitter_xml.language_xml","name":"language_xml","type":{".class":"CallableType","arg_kinds":[],"arg_names":[],"arg_types":[],"bound_args":[],"def_extras":{"first_arg":null},"fallback":"builtins.function","from_concatenate":false,"implicit":false,"imprecise_arg_kinds":false,"is_ellipsis_args":false,"name":"language_xml","ret_type":"builtins.object","type_guard":null,"type_is":null,"unpack_kwargs":false,"variables":[]}}}},"path":"/Users/willmcgugan/.pyenv/versions/3.11.1/envs/textual/lib/python3.11/site-packages/tree_sitter_xml/__init__.pyi"}